searchlite/__init__.py
searchlite/_parser.py
searchlite/optimized_multi_query_searcher.py
searchlite/providers.py
searchlite/searcher.py
searchlite-0.8.8.dist-info/LICENSE
searchlite-0.8.8.dist-info/METADATA
searchlite-0.8.8.dist-info/WHEEL
searchlite-0.8.8.dist-info/RECORD
