Metadata-Version: 2.1
Name: searchlite
Version: 0.8.8
Summary: fastest web search backed by selenium
Home-page: https://github.com/santhosh/
License: MIT
Author: Kammari Santhosh
Requires-Python: >=3.10,<4.0
Classifier: License :: OSI Approved :: MIT License
Classifier: Programming Language :: Python :: 3
Classifier: Programming Language :: Python :: 3.10
Classifier: Programming Language :: Python :: 3.11
Classifier: Programming Language :: Python :: 3.12
Classifier: Programming Language :: Python :: 3.13
Requires-Dist: parselite (>=0.3.13,<0.4.0)
Project-URL: Repository, https://github.com/santhosh/
